{
  "--storage-account-name": {
    "help": "storage account name", "default": "", "type": "str"
  },
  "--output-container-name": {
    "help": "output container name", "default": "", "type": "str"
  },
  "--output-folder-path": {
    "help": "output folder path", "default": "", "type": "str"
  },
  "--input-container-name": {
    "help": "input container name", "default": "", "type": "str"
  },
  "--input-folder-path": {
    "help": "input folder path", "default": "simulated_data/m365_emails", "type": "str"
  },
  "--application-id": {
    "help": "application id", "default": "", "type": "str"
  },
  "--directory-id": {
    "help": "directory id", "default": "", "type": "str"
  },
  "--adb-secret-scope-name": {
    "help": "secret scope name", "default": "gdc", "type": "str"
  },
  "--adb-sp-client-key-secret-name": {
    "help": "Azure Databricks Service Principal client key secret name in Databricks Secrets", "default": "gdc-service-principal-secret", "type": "str"
  },
  "--domain-expert-container-name": {
    "help": "domain expert container name", "default": "domain-experts", "type": "str"
  },
  "--domain-expert-folder-path": {
    "help": "domain expert folder path", "default": "domain_experts", "type": "str"
  },
  "--domain-expert-file-name": {
    "help": "domain expert file name", "default": "so_domain_expert.bin", "type": "str"
  },
  "--log-analytics-workspace-id": {
    "help": "Log Analytics workspace id", "default": "", "type": "str"
  },
  "--log-analytics-workspace-key-name": {
    "help": "Log Analytics workspace key secret name", "default": "log-analytics-api-key", "type": "str"
  },
  "--key-vault-url": {
    "help": "Azure Key Vault url", "default": "", "type": "str"
  }
}