{"id":"01cc3e7a-3e1b-40bd-b24d-9cfbcf119a14","deletedDateTime":null,"classification":null,"createdDateTime":"2021-10-20T07:30:46Z","description":null,"displayName":"DeniedUsersForSdfDvtGen2","expirationDateTime":null,"groupTypes":[],"isAssignableToRole":null,"mail":"deniedusersforsdfdvtgen2@contosotest4.onmicrosoft.com","mailEnabled":true,"mailNickname":"deniedusersforsdfdvtgen2","membershipRule":null,"membershipRuleProcessingState":null,"onPremisesDomainName":null,"onPremisesLastSyncDateTime":null,"onPremisesSyncEnabled":null,"preferredDataLocation":null,"preferredLanguage":null,"proxyAddresses":["SMTP:deniedusersforsdfdvtgen2@contosotest4.onmicrosoft.com"],"renewedDateTime":"2021-10-20T07:30:46Z","resourceProvisioningOptions":[],"securityEnabled":true,"securityIdentifier":"S-1-12-1-30162554-1086144027-4221324722-345641423","theme":null,"visibility":null,"ODataType":"#microsoft.graph.group","pObjectId":"01cc3e7a-3e1b-40bd-b24d-9cfbcf119a14","ptenant":"537d6c63-efb6-4922-8643-17921eb1b0dd","pAdditionalInfo":null,"datarow":0,"userrow":0,"pagerow":0,"rowinformation":{"errorInformation":null,"userReturnedNoData":false,"isUserSummaryRow":false,"userHasCompleteData":false}}
{"id":"aabf2ee7-519c-4601-9658-ca3cf21839cd","deletedDateTime":null,"classification":null,"createdDateTime":"2021-03-31T19:23:26Z","description":null,"displayName":"AllowedUsersForPdtDvtUK","expirationDateTime":null,"groupTypes":[],"isAssignableToRole":null,"mail":"AllowedUsersForPdtDvtUK@contosotest4.onmicrosoft.com","mailEnabled":true,"mailNickname":"AllowedUsersForPdtDvtUK","membershipRule":null,"membershipRuleProcessingState":null,"onPremisesDomainName":null,"onPremisesLastSyncDateTime":null,"onPremisesSyncEnabled":null,"preferredDataLocation":null,"preferredLanguage":null,"proxyAddresses":["SMTP:AllowedUsersForPdtDvtUK@contosotest4.onmicrosoft.com"],"renewedDateTime":"2021-03-31T19:23:26Z","resourceProvisioningOptions":[],"securityEnabled":true,"securityIdentifier":"S-1-12-1-2864656103-1174491548-1019893910-3443071218","theme":null,"visibility":null,"ODataType":"#microsoft.graph.group","pObjectId":"aabf2ee7-519c-4601-9658-ca3cf21839cd","ptenant":"537d6c63-efb6-4922-8643-17921eb1b0dd","pAdditionalInfo":null,"datarow":0,"userrow":0,"pagerow":0,"rowinformation":{"errorInformation":null,"userReturnedNoData":false,"isUserSummaryRow":false,"userHasCompleteData":false}}
{"id":"2e4b3b4a-6f37-466c-a21b-976ad4518e5a","deletedDateTime":null,"classification":null,"createdDateTime":"2021-10-20T06:25:25Z","description":null,"displayName":"DeniedUsersForPdtDvtGen2","expirationDateTime":null,"groupTypes":[],"isAssignableToRole":null,"mail":"deniedusersforpdtdvtgen2@contosotest4.onmicrosoft.com","mailEnabled":true,"mailNickname":"deniedusersforpdtdvtgen2","membershipRule":null,"membershipRuleProcessingState":null,"onPremisesDomainName":null,"onPremisesLastSyncDateTime":null,"onPremisesSyncEnabled":null,"preferredDataLocation":null,"preferredLanguage":null,"proxyAddresses":["SMTP:deniedusersforpdtdvtgen2@contosotest4.onmicrosoft.com"],"renewedDateTime":"2021-10-20T06:25:25Z","resourceProvisioningOptions":[],"securityEnabled":true,"securityIdentifier":"S-1-12-1-776682314-1181511479-1788287906-1519276500","theme":null,"visibility":null,"ODataType":"#microsoft.graph.group","pObjectId":"2e4b3b4a-6f37-466c-a21b-976ad4518e5a","ptenant":"537d6c63-efb6-4922-8643-17921eb1b0dd","pAdditionalInfo":null,"datarow":0,"userrow":0,"pagerow":0,"rowinformation":{"errorInformation":null,"userReturnedNoData":false,"isUserSummaryRow":false,"userHasCompleteData":false}}
{"id":"f026a7a2-c1ed-4d10-bfd2-df5772a0d3f4","deletedDateTime":null,"classification":null,"createdDateTime":"2018-07-16T12:18:55Z","description":"Groupa20c15f8-d466-4ad3-a650-4df826af4e22","displayName":"Groupa20c15f8","expirationDateTime":null,"groupTypes":["Unified"],"isAssignableToRole":null,"mail":"groupa20c15f8@contosotest4.onmicrosoft.com","mailEnabled":true,"mailNickname":"groupa20c15f8","membershipRule":null,"membershipRuleProcessingState":null,"onPremisesDomainName":null,"onPremisesLastSyncDateTime":null,"onPremisesSyncEnabled":null,"preferredDataLocation":null,"preferredLanguage":null,"proxyAddresses":["SPO:SPO_70e575f2-820c-4da1-832b-2118c56a4be8@SPO_537d6c63-efb6-4922-8643-17921eb1b0dd","SMTP:groupa20c15f8@contosotest4.onmicrosoft.com"],"renewedDateTime":"2018-07-16T12:18:55Z","resourceProvisioningOptions":[],"securityEnabled":false,"securityIdentifier":"S-1-12-1-4029065122-1292943853-1474286271-4107509874","theme":null,"visibility":"Public","ODataType":"#microsoft.graph.group","pObjectId":"f026a7a2-c1ed-4d10-bfd2-df5772a0d3f4","ptenant":"537d6c63-efb6-4922-8643-17921eb1b0dd","pAdditionalInfo":null,"datarow":0,"userrow":0,"pagerow":0,"rowinformation":{"errorInformation":null,"userReturnedNoData":false,"isUserSummaryRow":false,"userHasCompleteData":false}}
{"id":"39662603-3f65-4abb-98ac-1a0a02f0aaf2","deletedDateTime":null,"classification":null,"createdDateTime":"2018-05-01T18:38:03Z","description":null,"displayName":"testDl","expirationDateTime":null,"groupTypes":[],"isAssignableToRole":null,"mail":"testdl@contosotest4.onmicrosoft.com","mailEnabled":true,"mailNickname":"testDl","membershipRule":null,"membershipRuleProcessingState":null,"onPremisesDomainName":null,"onPremisesLastSyncDateTime":null,"onPremisesSyncEnabled":null,"preferredDataLocation":null,"preferredLanguage":null,"proxyAddresses":["SMTP:testdl@contosotest4.onmicrosoft.com"],"renewedDateTime":"2018-05-01T18:38:03Z","resourceProvisioningOptions":[],"securityEnabled":false,"securityIdentifier":"S-1-12-1-962995715-1253785445-169520280-4071288834","theme":null,"visibility":null,"ODataType":"#microsoft.graph.group","pObjectId":"39662603-3f65-4abb-98ac-1a0a02f0aaf2","ptenant":"537d6c63-efb6-4922-8643-17921eb1b0dd","pAdditionalInfo":null,"datarow":0,"userrow":0,"pagerow":0,"rowinformation":{"errorInformation":null,"userReturnedNoData":false,"isUserSummaryRow":false,"userHasCompleteData":false}}
{"id":"c3b42b09-cfc0-40db-a558-9ffa0b7fb0a6","deletedDateTime":null,"classification":null,"createdDateTime":"2019-06-11T00:15:08Z","description":null,"displayName":"AllowedUsersForPdtDvt","expirationDateTime":null,"groupTypes":[],"isAssignableToRole":null,"mail":"allowedusersforpdtdvt@contosotest4.onmicrosoft.com","mailEnabled":true,"mailNickname":"allowedusersforpdtdvt","membershipRule":null,"membershipRuleProcessingState":null,"onPremisesDomainName":null,"onPremisesLastSyncDateTime":null,"onPremisesSyncEnabled":null,"preferredDataLocation":null,"preferredLanguage":null,"proxyAddresses":["SMTP:allowedusersforpdtdvt@contosotest4.onmicrosoft.com"],"renewedDateTime":"2019-06-11T00:15:08Z","resourceProvisioningOptions":[],"securityEnabled":true,"securityIdentifier":"S-1-12-1-3283364617-1088147392-4204746917-2796584715","theme":null,"visibility":null,"ODataType":"#microsoft.graph.group","pObjectId":"c3b42b09-cfc0-40db-a558-9ffa0b7fb0a6","ptenant":"537d6c63-efb6-4922-8643-17921eb1b0dd","pAdditionalInfo":null,"datarow":0,"userrow":0,"pagerow":0,"rowinformation":{"errorInformation":null,"userReturnedNoData":false,"isUserSummaryRow":false,"userHasCompleteData":false}}
{"id":"a2db7abf-454a-4d13-9d88-6ebec9ec8cfe","deletedDateTime":null,"classification":null,"createdDateTime":"2019-06-10T20:49:53Z","description":null,"displayName":"AllowedUsersForSdfDvt","expirationDateTime":null,"groupTypes":[],"isAssignableToRole":null,"mail":"allowedusersforsdfdvt@contosotest4.onmicrosoft.com","mailEnabled":true,"mailNickname":"allowedusersforsdfdvt","membershipRule":null,"membershipRuleProcessingState":null,"onPremisesDomainName":null,"onPremisesLastSyncDateTime":null,"onPremisesSyncEnabled":null,"preferredDataLocation":null,"preferredLanguage":null,"proxyAddresses":["SMTP:allowedusersforsdfdvt@contosotest4.onmicrosoft.com"],"renewedDateTime":"2019-06-10T20:49:53Z","resourceProvisioningOptions":[],"securityEnabled":true,"securityIdentifier":"S-1-12-1-2732292799-1293108554-3194914973-4270648521","theme":null,"visibility":null,"ODataType":"#microsoft.graph.group","pObjectId":"a2db7abf-454a-4d13-9d88-6ebec9ec8cfe","ptenant":"537d6c63-efb6-4922-8643-17921eb1b0dd","pAdditionalInfo":null,"datarow":0,"userrow":0,"pagerow":0,"rowinformation":{"errorInformation":null,"userReturnedNoData":false,"isUserSummaryRow":false,"userHasCompleteData":false}}
{"id":"5075b7f0-918c-4dd8-a1c0-636ee02d42f6","deletedDateTime":null,"classification":null,"createdDateTime":"2018-06-13T04:06:23Z","description":"Contoso AI","displayName":"Contoso AI","expirationDateTime":null,"groupTypes":["Unified"],"isAssignableToRole":null,"mail":"Contosoai@contosotest4.onmicrosoft.com","mailEnabled":true,"mailNickname":"Contosoai","membershipRule":null,"membershipRuleProcessingState":null,"onPremisesDomainName":null,"onPremisesLastSyncDateTime":null,"onPremisesSyncEnabled":null,"preferredDataLocation":null,"preferredLanguage":null,"proxyAddresses":["SPO:SPO_52dc6520-f9b8-4d5c-b9f5-d6f1a5787bac@SPO_537d6c63-efb6-4922-8643-17921eb1b0dd","SMTP:Contosoai@contosotest4.onmicrosoft.com"],"renewedDateTime":"2018-06-13T04:06:23Z","resourceProvisioningOptions":[],"securityEnabled":false,"securityIdentifier":"S-1-12-1-1349892080-1306038668-1852031137-4131532256","theme":null,"visibility":"Public","ODataType":"#microsoft.graph.group","pObjectId":"5075b7f0-918c-4dd8-a1c0-636ee02d42f6","ptenant":"537d6c63-efb6-4922-8643-17921eb1b0dd","pAdditionalInfo":null,"datarow":0,"userrow":0,"pagerow":0,"rowinformation":{"errorInformation":null,"userReturnedNoData":false,"isUserSummaryRow":false,"userHasCompleteData":false}}
{"id":"de73a355-256d-495a-8a7a-38ba8dfa53ea","deletedDateTime":null,"classification":null,"createdDateTime":"2021-08-11T21:06:04Z","description":"Archimedes PPETesting from MGDC","displayName":"Archimedes-PPETest","expirationDateTime":null,"groupTypes":["Unified"],"isAssignableToRole":null,"mail":"Archimedes-PPETest@contosotest4.onmicrosoft.com","mailEnabled":true,"mailNickname":"Archimedes-PPETest","membershipRule":null,"membershipRuleProcessingState":null,"onPremisesDomainName":null,"onPremisesLastSyncDateTime":null,"onPremisesSyncEnabled":null,"preferredDataLocation":null,"preferredLanguage":null,"proxyAddresses":["SPO:SPO_baf83fa9-a504-45e4-889b-9e2449c4f06d@SPO_537d6c63-efb6-4922-8643-17921eb1b0dd","SMTP:Archimedes-PPETest@contosotest4.onmicrosoft.com"],"renewedDateTime":"2021-08-11T21:06:04Z","resourceProvisioningOptions":[],"securityEnabled":false,"securityIdentifier":"S-1-12-1-3732120405-1230644589-3124263562-3931372173","theme":null,"visibility":"Private","ODataType":"#microsoft.graph.group","pObjectId":"de73a355-256d-495a-8a7a-38ba8dfa53ea","ptenant":"537d6c63-efb6-4922-8643-17921eb1b0dd","pAdditionalInfo":null,"datarow":0,"userrow":0,"pagerow":0,"rowinformation":{"errorInformation":null,"userReturnedNoData":false,"isUserSummaryRow":false,"userHasCompleteData":false}}
{"id":"af7989d8-1851-4bba-9c2d-29c52cc7c104","deletedDateTime":null,"classification":null,"createdDateTime":"2019-06-08T01:04:38Z","description":null,"displayName":"DeniedUsersForPdtDvt","expirationDateTime":null,"groupTypes":["Unified"],"isAssignableToRole":null,"mail":"DeniedUsersForPdtDvt@contosotest4.onmicrosoft.com","mailEnabled":true,"mailNickname":"DeniedUsersForPdtDvt","membershipRule":null,"membershipRuleProcessingState":null,"onPremisesDomainName":null,"onPremisesLastSyncDateTime":null,"onPremisesSyncEnabled":null,"preferredDataLocation":null,"preferredLanguage":null,"proxyAddresses":["SPO:SPO_3ccfe57a-fc3c-44f6-ba14-ff76267ff49a@SPO_537d6c63-efb6-4922-8643-17921eb1b0dd","SMTP:DeniedUsersForPdtDvt@contosotest4.onmicrosoft.com"],"renewedDateTime":"2019-06-08T01:04:38Z","resourceProvisioningOptions":[],"securityEnabled":true,"securityIdentifier":"S-1-12-1-2943977944-1270487121-3307810204-79808300","theme":null,"visibility":"Public","ODataType":"#microsoft.graph.group","pObjectId":"af7989d8-1851-4bba-9c2d-29c52cc7c104","ptenant":"537d6c63-efb6-4922-8643-17921eb1b0dd","pAdditionalInfo":null,"datarow":0,"userrow":0,"pagerow":0,"rowinformation":{"errorInformation":null,"userReturnedNoData":false,"isUserSummaryRow":false,"userHasCompleteData":false}}
{"id":"b5bc456e-9e38-4cee-844b-7dd259c9d731","deletedDateTime":null,"classification":null,"createdDateTime":"2021-04-08T17:32:17Z","description":null,"displayName":"AllowedUsersForPDTGen2","expirationDateTime":null,"groupTypes":[],"isAssignableToRole":null,"mail":"AllowedUsersForPDTGen2@contosotest4.onmicrosoft.com","mailEnabled":true,"mailNickname":"AllowedUsersForPDTGen2","membershipRule":null,"membershipRuleProcessingState":null,"onPremisesDomainName":null,"onPremisesLastSyncDateTime":null,"onPremisesSyncEnabled":null,"preferredDataLocation":null,"preferredLanguage":null,"proxyAddresses":["SMTP:AllowedUsersForPDTGen2@contosotest4.onmicrosoft.com"],"renewedDateTime":"2021-04-08T17:32:17Z","resourceProvisioningOptions":[],"securityEnabled":true,"securityIdentifier":"S-1-12-1-3049014638-1290706488-3531426692-836225369","theme":null,"visibility":null,"ODataType":"#microsoft.graph.group","pObjectId":"b5bc456e-9e38-4cee-844b-7dd259c9d731","ptenant":"537d6c63-efb6-4922-8643-17921eb1b0dd","pAdditionalInfo":null,"datarow":0,"userrow":0,"pagerow":0,"rowinformation":{"errorInformation":null,"userReturnedNoData":false,"isUserSummaryRow":false,"userHasCompleteData":false}}
{"id":"c135ffcb-3760-4a35-a504-9274c42a9009","deletedDateTime":null,"classification":null,"createdDateTime":"2021-10-28T20:48:02Z","description":null,"displayName":"DeniedUsersForPdtDvtMailEnabled","expirationDateTime":null,"groupTypes":[],"isAssignableToRole":null,"mail":"DeniedUsersForPdtDvtMailEnabled@contosotest4.onmicrosoft.com","mailEnabled":true,"mailNickname":"DeniedUsersForPdtDvtMailEnabled","membershipRule":null,"membershipRuleProcessingState":null,"onPremisesDomainName":null,"onPremisesLastSyncDateTime":null,"onPremisesSyncEnabled":null,"preferredDataLocation":null,"preferredLanguage":null,"proxyAddresses":["SMTP:DeniedUsersForPdtDvtMailEnabled@contosotest4.onmicrosoft.com"],"renewedDateTime":"2021-10-28T20:48:02Z","resourceProvisioningOptions":[],"securityEnabled":true,"securityIdentifier":"S-1-12-1-3241541579-1245001568-1955726501-160443076","theme":null,"visibility":null,"ODataType":"#microsoft.graph.group","pObjectId":"c135ffcb-3760-4a35-a504-9274c42a9009","ptenant":"537d6c63-efb6-4922-8643-17921eb1b0dd","pAdditionalInfo":null,"datarow":0,"userrow":0,"pagerow":0,"rowinformation":{"errorInformation":null,"userReturnedNoData":false,"isUserSummaryRow":false,"userHasCompleteData":false}}
{"id":"651b347c-a8c3-4c9e-b2ec-bd258a534635","deletedDateTime":null,"classification":null,"createdDateTime":"2021-08-11T22:00:42Z","description":"Test Archimedes ODSP Dataset","displayName":"Test Archimedes ODSP Dataset","expirationDateTime":null,"groupTypes":["Unified"],"isAssignableToRole":null,"mail":"TestArchimedesODSPDataset@contosotest4.onmicrosoft.com","mailEnabled":true,"mailNickname":"TestArchimedesODSPDataset","membershipRule":null,"membershipRuleProcessingState":null,"onPremisesDomainName":null,"onPremisesLastSyncDateTime":null,"onPremisesSyncEnabled":null,"preferredDataLocation":null,"preferredLanguage":null,"proxyAddresses":["SPO:SPO_94cbccb4-f936-4985-a2e5-97354ff26144@SPO_537d6c63-efb6-4922-8643-17921eb1b0dd","SMTP:TestArchimedesODSPDataset@contosotest4.onmicrosoft.com"],"renewedDateTime":"2021-08-11T22:00:42Z","resourceProvisioningOptions":[],"securityEnabled":false,"securityIdentifier":"S-1-12-1-1696281724-1285466307-633203890-893801354","theme":null,"visibility":"Private","ODataType":"#microsoft.graph.group","pObjectId":"651b347c-a8c3-4c9e-b2ec-bd258a534635","ptenant":"537d6c63-efb6-4922-8643-17921eb1b0dd","pAdditionalInfo":null,"datarow":0,"userrow":0,"pagerow":0,"rowinformation":{"errorInformation":null,"userReturnedNoData":false,"isUserSummaryRow":false,"userHasCompleteData":false}}
{"id":"b133c4eb-139d-4961-ac51-7ba59575e038","deletedDateTime":null,"classification":null,"createdDateTime":"2020-07-24T21:48:49Z","description":"Denied users mail enabled sec group for pdt dvt ","displayName":"DeniedUsersGroupForPDTDvt","expirationDateTime":null,"groupTypes":[],"isAssignableToRole":null,"mail":null,"mailEnabled":false,"mailNickname":"f6943c53-7","membershipRule":null,"membershipRuleProcessingState":null,"onPremisesDomainName":null,"onPremisesLastSyncDateTime":null,"onPremisesSyncEnabled":null,"preferredDataLocation":null,"preferredLanguage":null,"proxyAddresses":[],"renewedDateTime":"2020-07-24T21:48:49Z","resourceProvisioningOptions":[],"securityEnabled":true,"securityIdentifier":"S-1-12-1-2972959979-1231098781-2776322476-954234261","theme":null,"visibility":null,"ODataType":"#microsoft.graph.group","pObjectId":"b133c4eb-139d-4961-ac51-7ba59575e038","ptenant":"537d6c63-efb6-4922-8643-17921eb1b0dd","pAdditionalInfo":null,"datarow":0,"userrow":0,"pagerow":0,"rowinformation":{"errorInformation":null,"userReturnedNoData":false,"isUserSummaryRow":false,"userHasCompleteData":false}}
{"id":"c7953f08-559a-4cad-a3cc-02263b4d8744","deletedDateTime":null,"classification":null,"createdDateTime":"2018-06-08T04:10:43Z","description":"Test Public Group","displayName":"Test Public Group","expirationDateTime":null,"groupTypes":["Unified"],"isAssignableToRole":null,"mail":"testpublicgroup@contosotest4.onmicrosoft.com","mailEnabled":true,"mailNickname":"testpublicgroup","membershipRule":null,"membershipRuleProcessingState":null,"onPremisesDomainName":null,"onPremisesLastSyncDateTime":null,"onPremisesSyncEnabled":null,"preferredDataLocation":null,"preferredLanguage":null,"proxyAddresses":["SPO:SPO_b380372d-0b1c-4cd3-b71f-1c8f9a914308@SPO_537d6c63-efb6-4922-8643-17921eb1b0dd","SMTP:testpublicgroup@contosotest4.onmicrosoft.com"],"renewedDateTime":"2018-06-08T04:10:43Z","resourceProvisioningOptions":[],"securityEnabled":false,"securityIdentifier":"S-1-12-1-3348446984-1286428058-637717667-1149717819","theme":null,"visibility":"Public","ODataType":"#microsoft.graph.group","pObjectId":"c7953f08-559a-4cad-a3cc-02263b4d8744","ptenant":"537d6c63-efb6-4922-8643-17921eb1b0dd","pAdditionalInfo":null,"datarow":0,"userrow":0,"pagerow":0,"rowinformation":{"errorInformation":null,"userReturnedNoData":false,"isUserSummaryRow":false,"userHasCompleteData":false}}
{"id":"9be41eaa-3486-44ae-b8ab-534034ea8452","deletedDateTime":null,"classification":null,"createdDateTime":"2021-04-30T21:46:26Z","description":null,"displayName":"Test-For-AdminPortal","expirationDateTime":null,"groupTypes":[],"isAssignableToRole":null,"mail":"Test-For-AdminPortal@contosotest4.onmicrosoft.com","mailEnabled":true,"mailNickname":"Test-For-AdminPortal","membershipRule":null,"membershipRuleProcessingState":null,"onPremisesDomainName":null,"onPremisesLastSyncDateTime":null,"onPremisesSyncEnabled":null,"preferredDataLocation":null,"preferredLanguage":null,"proxyAddresses":["SMTP:Test-For-AdminPortal@contosotest4.onmicrosoft.com"],"renewedDateTime":"2021-04-30T21:46:26Z","resourceProvisioningOptions":[],"securityEnabled":true,"securityIdentifier":"S-1-12-1-2615418538-1152267398-1079225272-1384442420","theme":null,"visibility":null,"ODataType":"#microsoft.graph.group","pObjectId":"9be41eaa-3486-44ae-b8ab-534034ea8452","ptenant":"537d6c63-efb6-4922-8643-17921eb1b0dd","pAdditionalInfo":null,"datarow":0,"userrow":0,"pagerow":0,"rowinformation":{"errorInformation":null,"userReturnedNoData":false,"isUserSummaryRow":false,"userHasCompleteData":false}}